redis_jwt_auth/__init__.py
redis_jwt_auth/cache_manager.py
redis_jwt_auth/middleware.py
redis_jwt_auth/token_validator.py
redis_jwt_auth-0.1.1.dist-info/LICENSE
redis_jwt_auth-0.1.1.dist-info/METADATA
redis_jwt_auth-0.1.1.dist-info/WHEEL
redis_jwt_auth-0.1.1.dist-info/top_level.txt
redis_jwt_auth-0.1.1.dist-info/RECORD
