Metadata-Version: 2.2
Name: redis-jwt-auth
Version: 0.1.1
Summary: A FastAPI Middleware for Secure JWT Authentication with Redis Caching
Home-page: https://github.com/parthsingh/redis-jwt-auth
Author: Parth Singh
Author-email: singhparth887@gmail.com
Classifier: Programming Language :: Python :: 3
Classifier: License :: OSI Approved :: MIT License
Classifier: Operating System :: OS Independent
Requires-Python: >=3.6
License-File: LICENSE
Requires-Dist: fastapi
Requires-Dist: redis
Requires-Dist: pyjwt
Dynamic: author
Dynamic: author-email
Dynamic: classifier
Dynamic: description
Dynamic: description-content-type
Dynamic: home-page
Dynamic: requires-dist
Dynamic: requires-python
Dynamic: summary
